odoo10_addon_stock_product_location_sorted_by_qty-10.0.1.0.0.99.dev12-py3.8-nspkg.pth
odoo/addons/stock_product_location_sorted_by_qty/README.rst
odoo/addons/stock_product_location_sorted_by_qty/__init__.py
odoo/addons/stock_product_location_sorted_by_qty/__manifest__.py
odoo/addons/stock_product_location_sorted_by_qty/i18n/de.po
odoo/addons/stock_product_location_sorted_by_qty/i18n/es.po
odoo/addons/stock_product_location_sorted_by_qty/i18n/fr.po
odoo/addons/stock_product_location_sorted_by_qty/i18n/sl.po
odoo/addons/stock_product_location_sorted_by_qty/i18n/stock_product_location_sorted_by_qty.pot
odoo/addons/stock_product_location_sorted_by_qty/models/__init__.py
odoo/addons/stock_product_location_sorted_by_qty/models/stock.py
odoo/addons/stock_product_location_sorted_by_qty/readme/CONTRIBUTORS.rst
odoo/addons/stock_product_location_sorted_by_qty/readme/DESCRIPTION.rst
odoo/addons/stock_product_location_sorted_by_qty/readme/USAGE.rst
odoo/addons/stock_product_location_sorted_by_qty/static/description/icon.png
odoo/addons/stock_product_location_sorted_by_qty/static/description/index.html
odoo/addons/stock_product_location_sorted_by_qty/static/description/stock_product_location_sorted_by_qty.png
odoo/addons/stock_product_location_sorted_by_qty/tests/__init__.py
odoo/addons/stock_product_location_sorted_by_qty/tests/test_product_location_sorted_by_qty.py
odoo/addons/stock_product_location_sorted_by_qty/views/stock_change_product_qty_view.xml
odoo10_addon_stock_product_location_sorted_by_qty-10.0.1.0.0.99.dev12.dist-info/METADATA
odoo10_addon_stock_product_location_sorted_by_qty-10.0.1.0.0.99.dev12.dist-info/WHEEL
odoo10_addon_stock_product_location_sorted_by_qty-10.0.1.0.0.99.dev12.dist-info/namespace_packages.txt
odoo10_addon_stock_product_location_sorted_by_qty-10.0.1.0.0.99.dev12.dist-info/top_level.txt
odoo10_addon_stock_product_location_sorted_by_qty-10.0.1.0.0.99.dev12.dist-info/RECORD
