Metadata-Version: 2.1
Name: odoo10-addon-stock-product-location-sorted-by-qty
Version: 10.0.1.0.0.99.dev12
Summary: In the update wizard of quantities for a product, sort the stock location by quantity
Home-page: https://github.com/OCA/stock-logistics-warehouse
Author: Akretion, Odoo Community Association (OCA)
Author-email: support@odoo-community.org
License: AGPL-3
Platform: UNKNOWN
Classifier: Programming Language :: Python
Classifier: Framework :: Odoo
Classifier: Framework :: Odoo :: 10.0
Classifier: License :: OSI Approved :: GNU Affero General Public License v3
Classifier: Development Status :: 5 - Production/Stable
Requires-Python: ~=2.7
Requires-Dist: odoo <10.1dev,>=10.0
